<keymap version="1" name="MyDefault" parent="Mac OS X 10.5+">
  <action id="$Cut">
    <keyboard-shortcut first-keystroke="meta x" />
  </action>
  <action id="$Delete">
    <keyboard-shortcut first-keystroke="delete" />
    <keyboard-shortcut first-keystroke="back_space" />
  </action>
  <action id="$Redo">
    <keyboard-shortcut first-keystroke="shift meta z" />
  </action>
  <action id="AddToFavoritesPopup" />
  <action id="Arrangement.Alias.Rule.Remove">
    <keyboard-shortcut first-keystroke="delete" />
    <keyboard-shortcut first-keystroke="back_space" />
  </action>
  <action id="Arrangement.Rule.Remove">
    <keyboard-shortcut first-keystroke="delete" />
    <keyboard-shortcut first-keystroke="back_space" />
  </action>
  <action id="ChangesView.GroupBy.Directory" />
  <action id="CheckinProject" />
  <action id="CompareTwoFiles" />
  <action id="CopyPaths" />
  <action id="CopyReference" />
  <action id="DecrementWindowHeight" />
  <action id="Diff.ShowDiff" />
  <action id="DomElementsTreeView.DeleteElement">
    <keyboard-shortcut first-keystroke="delete" />
    <keyboard-shortcut first-keystroke="back_space" />
  </action>
  <action id="EditSource" />
  <action id="EditorAddRectangularSelectionOnMouseDrag" />
  <action id="EditorChooseLookupItemDot" />
  <action id="EditorCodeBlockEnd" />
  <action id="EditorCodeBlockEndWithSelection" />
  <action id="EditorCodeBlockStart" />
  <action id="EditorCodeBlockStartWithSelection" />
  <action id="EditorCompleteStatement" />
  <action id="EditorContextInfo" />
  <action id="EditorCreateRectangularSelection" />
  <action id="EditorCreateRectangularSelectionOnMouseDrag" />
  <action id="EditorCutLineEnd" />
  <action id="EditorDeleteLine" />
  <action id="EditorDeleteToLineStart">
    <keyboard-shortcut first-keystroke="meta back_space" />
  </action>
  <action id="EditorDown">
    <keyboard-shortcut first-keystroke="down" />
  </action>
  <action id="EditorDuplicate" />
  <action id="EditorFocusGutter" />
  <action id="EditorJoinLines" />
  <action id="EditorLeft">
    <keyboard-shortcut first-keystroke="left" />
  </action>
  <action id="EditorLineEnd">
    <keyboard-shortcut first-keystroke="meta right" />
  </action>
  <action id="EditorLineEndWithSelection">
    <keyboard-shortcut first-keystroke="shift meta right" />
  </action>
  <action id="EditorLineStart">
    <keyboard-shortcut first-keystroke="meta left" />
  </action>
  <action id="EditorLineStartWithSelection">
    <keyboard-shortcut first-keystroke="shift meta left" />
  </action>
  <action id="EditorMatchBrace">
    <keyboard-shortcut first-keystroke="home" />
    <keyboard-shortcut first-keystroke="end" />
  </action>
  <action id="EditorPasteFromX11" />
  <action id="EditorPasteSimple" />
  <action id="EditorRight">
    <keyboard-shortcut first-keystroke="right" />
  </action>
  <action id="EditorSelectWord" />
  <action id="EditorShowGutterIconTooltip" />
  <action id="EditorSplitLine" />
  <action id="EditorStartNewLineBefore" />
  <action id="EditorTextEnd">
    <keyboard-shortcut first-keystroke="meta down" />
  </action>
  <action id="EditorTextEndWithSelection">
    <keyboard-shortcut first-keystroke="shift meta down" />
  </action>
  <action id="EditorTextStart">
    <keyboard-shortcut first-keystroke="meta up" />
  </action>
  <action id="EditorTextStartWithSelection">
    <keyboard-shortcut first-keystroke="shift meta up" />
  </action>
  <action id="EditorToggleCase">
    <keyboard-shortcut first-keystroke="meta u" />
  </action>
  <action id="EditorToggleColumnMode" />
  <action id="EditorUnSelectWord" />
  <action id="EditorUp">
    <keyboard-shortcut first-keystroke="up" />
  </action>
  <action id="EmojiAndSymbols" />
  <action id="ExpressionTypeInfo" />
  <action id="ExternalJavaDoc" />
  <action id="FileChooser.GotoDesktop" />
  <action id="FileChooser.TogglePathShowing" />
  <action id="FindNext" />
  <action id="FindPrevious" />
  <action id="FindUsages" />
  <action id="FindUsagesInFile" />
  <action id="GotoClass">
    <keyboard-shortcut first-keystroke="meta o" />
    <keyboard-shortcut first-keystroke="meta t" />
  </action>
  <action id="GotoNextElementUnderCaretUsage" />
  <action id="GotoPrevElementUnderCaretUsage" />
  <action id="GotoSuperMethod" />
  <action id="Graph.Delete">
    <keyboard-shortcut first-keystroke="delete" />
    <keyboard-shortcut first-keystroke="back_space" />
  </action>
  <action id="HighlightUsagesInFile" />
  <action id="IncrementWindowHeight" />
  <action id="MoveStatementDown" />
  <action id="MoveStatementUp" />
  <action id="ParameterInfo" />
  <action id="QuickImplementations" />
  <action id="QuickJavaDoc" />
  <action id="ReformatCode">
    <keyboard-shortcut first-keystroke="shift alt f" />
  </action>
  <action id="ResizeToolWindowDown" />
  <action id="ResizeToolWindowUp" />
  <action id="RiderOpenSolution" />
  <action id="RiderUnitTestCoverSolutionAction">
    <keyboard-shortcut first-keystroke="meta k" />
  </action>
  <action id="RunDashboard.RemoveConfiguration">
    <keyboard-shortcut first-keystroke="delete" />
    <keyboard-shortcut first-keystroke="back_space" />
  </action>
  <action id="RunDashboard.UngroupConfigurations">
    <keyboard-shortcut first-keystroke="delete" />
    <keyboard-shortcut first-keystroke="back_space" />
  </action>
  <action id="SearchEverywhere.NavigateToNextGroup">
    <keyboard-shortcut first-keystroke="page_down" />
  </action>
  <action id="SearchEverywhere.NavigateToPrevGroup">
    <keyboard-shortcut first-keystroke="page_up" />
  </action>
  <action id="SelectAllOccurrences" />
  <action id="SelectNextOccurrence">
    <keyboard-shortcut first-keystroke="meta d" />
  </action>
  <action id="SendEOF" />
  <action id="ShowErrorDescription" />
  <action id="ShowNavBar">
    <keyboard-shortcut first-keystroke="alt home" />
  </action>
  <action id="ShowSettings" />
  <action id="ShowSettingsAndFindUsages" />
  <action id="ShowUsages" />
  <action id="Synchronize" />
  <action id="TodoViewGroupByShowPackages" />
  <action id="UnselectPreviousOccurrence" />
  <action id="Vcs.UpdateProject" />
  <action id="XDebugger.RemoveWatch">
    <keyboard-shortcut first-keystroke="delete" />
    <keyboard-shortcut first-keystroke="back_space" />
  </action>
</keymap>